MANIFEST.in
README.rst
setup.cfg
setup.py
docs/HISTORY.rst
docs/INSTALL.rst
docs/LICENSE.GPL
docs/LICENSE.txt
plonegovmy/__init__.py
plonegovmy.theme.egg-info/PKG-INFO
plonegovmy.theme.egg-info/SOURCES.txt
plonegovmy.theme.egg-info/dependency_links.txt
plonegovmy.theme.egg-info/entry_points.txt
plonegovmy.theme.egg-info/namespace_packages.txt
plonegovmy.theme.egg-info/not-zip-safe
plonegovmy.theme.egg-info/paster_plugins.txt
plonegovmy.theme.egg-info/requires.txt
plonegovmy.theme.egg-info/top_level.txt
plonegovmy/theme/__init__.py
plonegovmy/theme/configure.zcml
plonegovmy/theme/interfaces.py
plonegovmy/theme/setuphandlers.py
plonegovmy/theme/browser/README.txt
plonegovmy/theme/browser/__init__.py
plonegovmy/theme/jbot/README.txt
plonegovmy/theme/locales/README.txt
plonegovmy/theme/profiles/default/browserlayer.xml
plonegovmy/theme/profiles/default/cssregistry.xml
plonegovmy/theme/profiles/default/jsregistry.xml
plonegovmy/theme/profiles/default/metadata.xml
plonegovmy/theme/profiles/default/plonegovmy.theme.marker.txt
plonegovmy/theme/profiles/default/skins.xml
plonegovmy/theme/profiles/default/theme.xml
plonegovmy/theme/skins/plonegovmy_theme/README.txt
plonegovmy/theme/static/README.txt
plonegovmy/theme/static/index.html
plonegovmy/theme/static/rules.xml
plonegovmy/theme/static/style.css
plonegovmy/theme/static/css/public.css
plonegovmy/theme/static/img/bg.jpg
plonegovmy/theme/upgrades/__init__.py
plonegovmy/theme/upgrades/handlers.py
plonegovmy/theme/upgrades/profiles.py